ncs/__init__.py
ncs/api.py
ncs/db.py
ncs-0.1.0.dist-info/DESCRIPTION.rst
ncs-0.1.0.dist-info/METADATA
ncs-0.1.0.dist-info/RECORD
ncs-0.1.0.dist-info/WHEEL
ncs-0.1.0.dist-info/metadata.json
ncs-0.1.0.dist-info/top_level.txt
