Metadata-Version: 2.0
Name: ncs
Version: 0.1.0
Summary: NCS<->RGB color database for Python
Home-page: https://github.com/5monkeys/python-ncs
Author: Christopher Rosell
Author-email: chrippa@5monkeys.se
License: MIT license
Keywords: ncs
Platform: UNKNOWN
Classifier: Development Status :: 2 - Pre-Alpha
Classifier: Intended Audience :: Developers
Classifier: License :: OSI Approved :: MIT License
Classifier: Natural Language :: English
Classifier: Programming Language :: Python :: 2
Classifier: Programming Language :: Python :: 2.7
Classifier: Programming Language :: Python :: 3
Classifier: Programming Language :: Python :: 3.3
Classifier: Programming Language :: Python :: 3.4
Classifier: Programming Language :: Python :: 3.5
